infomedia_correlation_hash.py
infomedia_correlation_hash-0.2.dist-info/METADATA
infomedia_correlation_hash-0.2.dist-info/WHEEL
infomedia_correlation_hash-0.2.dist-info/top_level.txt
infomedia_correlation_hash-0.2.dist-info/RECORD
