Metadata-Version: 2.1
Name: infomedia-correlation-hash
Version: 0.2
Summary: A package to generate unique correlation hashes using UUID.
Classifier: Programming Language :: Python :: 3
Classifier: License :: OSI Approved :: MIT License
Classifier: Operating System :: OS Independent
Requires-Python: >=3.6
